wdlc/__init__.py
wdlc/cli.py
wdlc/utils.py
wdlc/wdlc.py
wdlc-0.9.1.dist-info/METADATA
wdlc-0.9.1.dist-info/WHEEL
wdlc-0.9.1.dist-info/entry_points.txt
wdlc-0.9.1.dist-info/top_level.txt
wdlc-0.9.1.dist-info/RECORD
