Metadata-Version: 2.4
Name: wdlc
Version: 0.9.1
Summary: Web DL Compiler
Author-email: "@wdlc" <you@example.com>
License: MIT
Requires-Python: >=3.8
Requires-Dist: torch
Requires-Dist: numpy
Requires-Dist: psutil>=5.9
